dbo/__init__.py
dbo/dbo.py
dbo/query.py
mih_dbo-1.1.0.dist-info/METADATA
mih_dbo-1.1.0.dist-info/WHEEL
mih_dbo-1.1.0.dist-info/namespace_packages.txt
mih_dbo-1.1.0.dist-info/top_level.txt
mih_dbo-1.1.0.dist-info/zip-safe
mih_dbo-1.1.0.dist-info/RECORD
