Metadata-Version: 2.1
Name: mih-dbo
Version: 1.1.0
Summary: UNKNOWN
Home-page: UNKNOWN
Author: MIH
Author-email: UNKNOWN
License: UNKNOWN
Platform: UNKNOWN
Classifier: Development Status :: 3 - Alpha
Classifier: Programming Language :: Python
Requires-Dist: mih-config (==1.0.0)
Requires-Dist: mysql-connector (>=2.1.6)
Requires-Dist: mysqlclient (>=1.4.2)
Requires-Dist: SQLAlchemy (>=1.3.1)
